outline_wiki_api/__init__.py
outline_wiki_api/client.py
outline_wiki_api/const.py
outline_wiki_api/exceptions.py
outline_wiki_api/utils.py
outline_wiki_api/models/__init__.py
outline_wiki_api/models/auth.py
outline_wiki_api/models/collection.py
outline_wiki_api/models/document.py
outline_wiki_api/models/event.py
outline_wiki_api/models/membership.py
outline_wiki_api/models/response.py
outline_wiki_api/models/team.py
outline_wiki_api/models/user.py
outline_wiki_api/models/view.py
outline_wiki_api/resources/__init__.py
outline_wiki_api/resources/auth.py
outline_wiki_api/resources/base.py
outline_wiki_api/resources/collections.py
outline_wiki_api/resources/comments.py
outline_wiki_api/resources/documents.py
outline_wiki_api/resources/events.py
outline_wiki_api/resources/users.py
outline_wiki_api/resources/views.py
outline_wiki_api-0.3.2.dist-info/METADATA
outline_wiki_api-0.3.2.dist-info/WHEEL
outline_wiki_api-0.3.2.dist-info/licenses/LICENSE
outline_wiki_api-0.3.2.dist-info/licenses/NOTICE
outline_wiki_api-0.3.2.dist-info/RECORD
