Metadata-Version: 2.4
Name: outline_wiki_api
Version: 0.3.2
Summary: A python API for Outline Wiki.
Project-URL: GitHub, https://github.com/eppv/outline-wiki-api
Author-email: eppv <evgeniypalych@gmail.com>
License: Outline Wiki Python API
License-File: LICENSE
License-File: NOTICE
Requires-Python: >=3.12
Requires-Dist: httpx>=0.28.0
Requires-Dist: pydantic>=2.10.0
Requires-Dist: pydantic[email]
Provides-Extra: test
Requires-Dist: pytest-cov>=4.0.0; extra == 'test'
Requires-Dist: pytest-mock>=3.10.0; extra == 'test'
Requires-Dist: pytest>=7.0.0; extra == 'test'
